Workbook

Sheet README
A1: Mirae Corporation (025560) — DCF
A3: GENERATED FILE — do not hand-edit. Re-run build_dcf_xlsx.py after any new DART filing.
A4: Contracts and quarterly actuals are read live from index.html, so this workbook cannot drift from the dashboard.
A6: Edit only the BLUE cells on the Assumptions sheet. Everything else is a formula.
A8: WHAT IS MEASURED (from DART, FY25 사업보고서 rcept 20260319001166):
A9: Order book: 22 contracts, reconciled against all 29 단일판매·공급계약 filings. Total 115.48bn.
A10: Quarterly segment revenue Q1'25..Q1'26; FY25 consolidated BS + CF; note 30 tax detail.
A12: WHAT IS ASSUMED (and therefore where the answer actually comes from):
A13: FY2027+ revenue growth. The order book runs dry after Q3'27 — only 3.58bn is contracted beyond FY26.
A14: WACC and terminal growth. Terminal value will dominate; see the Sensitivity sheet before believing any
A15: single fair-value number. With 5 quarters of actuals on a company that just 5x'd quarterly revenue,
A16: this model is a disciplined way to express assumptions — not a measurement of intrinsic value.
... A44: - Cost of equity / WACC is an input, not derived. No beta study was done.

Sheet Assumptions
A1: ASSUMPTIONS — edit blue cells only
A3: OPERATING
A4: Base / sub-threshold ATE (bn/qtr) | B4: 5 | D4: Not disclosed. Ran ~4.6bn/qtr in H1'25 before any big contract delivered.
A5: MAI revenue (bn/qtr) | B5: 2 | D5: Volatile 0.85-3.39, avg ~1.8. Model absolute, NOT % of revenue — it is independent of ATE.
A6: Gross margin % | B6: 0.42 | D6: Actuals swing 34.6-56.7% with mix. FY25 blended ~41%.
A7: SG&A (bn/qtr) | B7: 2.4 | D7: ~FIXED: ran 2.3bn on both a 4.75bn and a 22.6bn revenue quarter. Operating leverage is the thesis.
A8: R&D (bn/qtr) | B8: 0.12 | D8: Also ~fixed, small.
A9: Revenue growth FY2027+ % | B9: 0.1 | D9: PURE ASSUMPTION. Order book is dry after Q3'27 (only 3.58bn contracted). Drives most of the answer.
A11: WORKING CAPITAL <-- the most consequential input
A12: NWC as % of revenue | B12: 0.735 | D12: FY25 actual: 37.35/50.78 = 73.6%. Set lower only if you believe the ramp brings WC efficiency.
A14: CAPITAL / VALUATION
A15: Capex (bn/yr) | B15: 0.3 | D15: FY25 actual only 0.084bn (<0.2% of revenue). Asset-light. Raised slightly for a ramp.
A16: D&A (bn/yr) | B16: 0.85 | D16: FY25: 0.817 depreciation + 0.024 amortisation.
A17: WACC | B17: 0.12 | D17: INPUT, not derived. No beta study done. See Sensitivity.
A18: Terminal growth | B18: 0.02 | D18: TV will dominate EV — check the Sensitivity sheet.
A20: TAX
A21: Statutory rate | B21: 0.209 | D21: 2.05bn / 9.83bn per note 30-(2).
A22: NOL offset % of taxable income | B22: 1 | D22: 100% = SME (조특법 제6조①). 80% only if 나목 breached (>=500bn-asset holder takes >=30%) — no grace.
A23: Minimum tax (최저한세) floor % | B23: 0.07 | D23: SME rate. Floors CREDIT usage, not NOL usage. SECONDARY-sourced — verify before relying on it.
A25: CAPITAL STRUCTURE
A26: Shares (M, fully diluted) | B26: 27.778678 | D26: Assumes the 2.32M placement closes 2026-07-27. Excludes convertible-bond dilution.
A27: Net debt (bn) | B27: 4.95 | D27: Debt 7.45 + CB 7.46 + lease 0.91 - cash 10.87. CB dilution NOT in share count.
A28: Investment property (bn) | B28: 53.25 | D28: Non-operating; added to EV at book. 35% of total assets.

Sheet OrderBook
A1: Order date | B1: Counterparty | C1: Segment | D1: Memory | E1: Value (bn) | F1: Delivery | G1: Delivery Q | H1: Delivery FY | I1: Terms
A2: 2025-06-26 | B2: CXMT | C2: China-localization | D2: DRAM | E2: 3.49 | F2: 2025-07-25 | G2: 2025-Q3 | H2: 2025 | I2: 50% pre-ship / 50% post-approval
A3: 2025-07-14 | B3: CXMT | C3: China-localization | D3: DRAM | E3: 3.52 | F3: 2025-08-22 | G3: 2025-Q3 | H3: 2025 | I3: 50% pre-ship / 50% post-approval
A4: 2025-08-06 | B4: CXMT | C4: China-localization | D4: DRAM | E4: 5.69 | F4: 2025-09-30 | G4: 2025-Q3 | H4: 2025 | I4: 50% pre-ship / 50% post-approval
A5: 2025-08-21 | B5: CXMT | C5: China-localization | D5: DRAM | E5: 1.1 | F5: 2025-10-31 | G5: 2025-Q4 | H5: 2025 | I5: parts contract (amended 2024 order; DART 발주일 2024-09-02, date= amendment filing date). Delivery 08-31->10-31 per rcp 20250821800391
A6: 2025-08-21 | B6: CXMT | C6: China-localization | D6: DRAM | E6: 5.83 | F6: 2025-10-31 | G6: 2025-Q4 | H6: 2025 | I6: 80% pre-delivery / 20% balance (amended 2024 order; DART 발주일 2024-08-22, date= amendment filing date). Delivery 08-31->10-31 per rcp 20250821800390
A7: 2025-09-08 | B7: YILING TRADING | C7: China-localization | D7: Mixed | E7: 4.99 | F7: 2025-10-30 | G7: 2025-Q4 | H7: 2025 | I7: 50% pre-ship / 50% post-approval
A8: 2025-09-08 | B8: YILING TRADING | C8: China-localization | D8: Mixed | E8: 3.19 | F8: 2025-11-30 | G8: 2025-Q4 | H8: 2025 | I8: 50% pre-ship / 50% post-approval
A9: 2025-11-26 | B9: YILING TRADING | C9: China-localization | D9: Mixed | E9: 13.85 | F9: 2026-04-30 | G9: 2026-Q2 | H9: 2026 | I9: 50% pre-ship / 50% post-approval
A10: 2025-12-19 | B10: Unimos Microelectronics (Wuhan) | C10: China-localization | D10: Mixed | E10: 10.2 | F10: 2026-04-20 | G10: 2026-Q2 | H10: 2026 | I10: 90% within 30d of arrival / 10% post-approval (delivery amended 2026-03-25->04-20 per rcp 20260325801220 — moves Q1'26->Q2'26)
A11: 2026-02-26 | B11: Unimos Microelectronics (Wuhan) | C11: China-localization | D11: Mixed | E11: 3.3 | F11: 2026-06-30 | G11: 2026-Q2 | H11: 2026 | I11: 90% within 30d of arrival / 10% post-approval
A12: 2026-03-12 | B12: YILING TRADING | C12: China-localization | D12: Mixed | E12: 6.19 | F12: 2026-08-25 | G12: 2026-Q3 | H12: 2026 | I12: 70% pre-ship / 30% post-approval (delivery amended 7/25→8/25, product spec change)
A13: 2026-03-12 | B13: Unimos Microelectronics (Wuhan) | C13: China-localization | D13: Mixed | E13: 1.69 | F13: 2026-07-15 | G13: 2026-Q3 | H13: 2026 | I13: 90% within 30d of arrival / 10% post-approval (delivery amended 6/30→7/15)
... A23: 2026-06-23 | B23: YILING TRADING | C23: China-localization | D23: Mixed | E23: 6.22 | F23: 2026-11-20 | G23: 2026-Q4 | H23: 2026 | I23: 70% pre-ship / 30% post-approval
D24: TOTAL | E24: =SUM(E2:E23)
A26: Reconciled against all 29 단일판매·공급계약 filings (2025-01..2026-07); 29 -> 22 distinct after deduping [기재정정] revisions. Delivery = 계약기간 종료일 = deliver-BY deadline, not actual delivery — Mirae ships early, so this LAGS revenue.

Sheet Actuals
A1: QUARTERLY ACTUALS (KRW bn) — DART 매출실적 + stockanalysis margins
B2: 2025-Q1 | C2: 2025-Q2 | D2: 2025-Q3 | E2: 2025-Q4 | F2: 2026-Q1
A3: ATE revenue | B3: 3.634 | C3: 5.537 | D3: 21.781 | E3: 14.24 | F3: 17.35
A4: MAI revenue | B4: 1.114 | C4: 1.27 | D4: 0.847 | E4: 2.355 | F4: 3.389
A5: Total revenue | B5: 4.749 | C5: 6.806 | D5: 22.628 | E5: 16.595 | F5: 20.738
A6: Gross margin % | B6: 56.74 | C6: 42.22 | D6: 36.36 | E6: 44.7 | F6: 34.55
A7: SG&A | B7: 2.242 | C7: 1.713 | D7: 2.138 | E7: 2.991 | F7: 2.528
A8: R&D | B8: 0.178 | C8: 0.085 | D8: 0.105 | E8: 0.145 | F8: 0.118
A9: Operating profit | B9: 0.292 | C9: 1.041 | D9: 6.01 | E9: 1.811 | F9: 4.887
A11: FY2025 BALANCE SHEET / CASH FLOW (consolidated, rcept 20260319001166)
A12: Cash | B12: 10.87
A13: Receivables | B13: 12.08
A14: Inventory | B14: 34.64
A15: Payables | B15: 9.37
A16: Short-term debt | B16: 7.45
A17: Convertible bonds | B17: 7.46
A18: Lease liabilities | B18: 0.91
A19: Investment property | B19: 53.25
A20: PP&E | B20: 16.99
A21: Total assets | B21: 152.35
A22: Equity | B22: 122.6
A23: Depreciation | B23: 0.817
... A28: NWC % of revenue | B28: 0.7355258
A29: FY24 NWC was 23.26bn -> dWC consumed 14.1bn of cash in FY25, vs 9.83bn pretax income. Cash fell 13.50 -> 10.87.

Sheet NOL
A1: TAX LOSS WATERFALL — expiry-ordered (note 30-(4)/(5), at 2025-12-31)
A3: Expiry bucket | B3: Amount (bn)
A4: Expires 2026 | B4: 2.45
A5: Expires 2027 | B5: 27.1
A6: Expires 2028 | B6: 10.46
A7: Expires 2029+ | B7: 25.39
A8: TOTAL | B8: =SUM(B4:B7)
A10: 29.55bn (45%) expires by end-2027. Use-it-or-lose-it: only taxable income earned NOW saves it. This — not the 80/100% cap — is the binding constraint.
A12: CONSUMPTION BY YEAR
B13: 2026 | C13: 2027 | D13: 2028 | E13: 2029 | F13: 2030
A14: Taxable income (pre-NOL) | B14: =Model!B10 | C14: =Model!C10 | D14: =Model!D10 | E14: =Model!E10 | F14: =Model!F10
A15: NOL available | B15: =SUM(B4:B7) | C15: =B18 | D15: =C18 | E15: =D18 | F15: =E18
A16: NOL used | B16: =MAX(0,MIN(B15,B14*Assumptions!$B$22)) | C16: =MAX(0,MIN(C15,C14*Assumptions!$B$22)) | D16: =MAX(0,MIN(D15,D14*Assumptions!$B$22)) | E16: =MAX(0,MIN(E15,E14*Assumptions!$B$22)) | F16: =MAX(0,MIN(F15,F14*Assumptions!$B$22))
A17: NOL expired unused | B17: =MAX(0,B4-B16) | C17: =MAX(0,B5-C16) | D17: =MAX(0,B6-D16) | E17: 0 | F17: 0 | H17: Simplification: expires the whole dated bucket less that year's usage. With income this large the buckets drain first, so this is conservative-neutral; revisit if EBIT assumptions fall a lot.
A18: NOL closing balance | B18: =MAX(0,B15-B16-B17) | C18: =MAX(0,C15-C16-C17) | D18: =MAX(0,D15-D16-D17) | E18: =MAX(0,E15-E16-E17) | F18: =MAX(0,F15-F16-F17)
A19: Taxable after NOL | B19: =MAX(0,B14-B16) | C19: =MAX(0,C14-C16) | D19: =MAX(0,D14-D16) | E19: =MAX(0,E14-E16) | F19: =MAX(0,F14-F16)
A20: Tax at statutory | B20: =B19*Assumptions!$B$21 | C20: =C19*Assumptions!$B$21 | D20: =D19*Assumptions!$B$21 | E20: =E19*Assumptions!$B$21 | F20: =F19*Assumptions!$B$21
A21: Minimum tax floor | B21: =B19*Assumptions!$B$23 | C21: =C19*Assumptions!$B$23 | D21: =D19*Assumptions!$B$23 | E21: =E19*Assumptions!$B$23 | F21: =F19*Assumptions!$B$23
A22: Credits available | B22: 4.61 | C22: =B24 | D22: =C24 | E22: =D24 | F22: =E24
A23: Credits used | B23: =MAX(0,MIN(B22,B20-B21)) | C23: =MAX(0,MIN(C22,C20-C21)) | D23: =MAX(0,MIN(D22,D20-D21)) | E23: =MAX(0,MIN(E22,E20-E21)) | F23: =MAX(0,MIN(F22,F20-F21))
A24: Credits closing | B24: =B22-B23 | C24: =C22-C23 | D24: =D22-D23 | E24: =E22-E23 | F24: =F22-F23
A26: Credits (4.61bn) offset tax only down to the 최저한세 floor — they cannot take cash tax to zero. The floor applies to the base AFTER the NOL deduction (이월결손금 is a 법인세법 제13조 deduction, not a 조특법 특례, so it is not added back).

Sheet Model
A1: DCF MODEL (KRW bn) — all figures annual
B2: 2026 | C2: 2027 | D2: 2028 | E2: 2029 | F2: 2030
A3: Order book (contracted) | B3: 84.09 | C3: 3.58 | D3: 0 | E3: 0 | F3: 0 | H3: Dry after FY2027 — 3.58bn only.
A4: Base ATE | B4: =Assumptions!$B$4*4 | C4: =Assumptions!$B$4*4 | D4: =Assumptions!$B$4*4 | E4: =Assumptions!$B$4*4 | F4: =Assumptions!$B$4*4
A5: MAI | B5: =Assumptions!$B$5*4 | C5: =Assumptions!$B$5*4 | D5: =Assumptions!$B$5*4 | E5: =Assumptions!$B$5*4 | F5: =Assumptions!$B$5*4
A6: Revenue | B6: =SUM(B3:B5) | C6: =B6*(1+Assumptions!$B$9) | D6: =C6*(1+Assumptions!$B$9) | E6: =D6*(1+Assumptions!$B$9) | F6: =E6*(1+Assumptions!$B$9) | H6: FY26 = contracted + base. FY27+ = growth assumption.
A7: Gross profit | B7: =B6*Assumptions!$B$6 | C7: =C6*Assumptions!$B$6 | D7: =D6*Assumptions!$B$6 | E7: =E6*Assumptions!$B$6 | F7: =F6*Assumptions!$B$6
A8: SG&A | B8: =Assumptions!$B$7*4 | C8: =Assumptions!$B$7*4 | D8: =Assumptions!$B$7*4 | E8: =Assumptions!$B$7*4 | F8: =Assumptions!$B$7*4
A9: R&D | B9: =Assumptions!$B$8*4 | C9: =Assumptions!$B$8*4 | D9: =Assumptions!$B$8*4 | E9: =Assumptions!$B$8*4 | F9: =Assumptions!$B$8*4
A10: EBIT | B10: =B7-B8-B9 | C10: =C7-C8-C9 | D10: =D7-D8-D9 | E10: =E7-E8-E9 | F10: =F7-F8-F9
A11: EBIT margin | B11: =IFERROR(B10/B6,0) | C11: =IFERROR(C10/C6,0) | D11: =IFERROR(D10/D6,0) | E11: =IFERROR(E10/E6,0) | F11: =IFERROR(F10/F6,0)
A13: Taxable income | B13: =NOL!B14 | C13: =NOL!C14 | D13: =NOL!D14 | E13: =NOL!E14 | F13: =NOL!F14
A14: less NOL used | B14: =-NOL!B16 | C14: =-NOL!C16 | D14: =-NOL!D16 | E14: =-NOL!E16 | F14: =-NOL!F16
A15: Taxable after NOL | B15: =NOL!B19 | C15: =NOL!C19 | D15: =NOL!D19 | E15: =NOL!E19 | F15: =NOL!F19
A16: Tax at statutory | B16: =NOL!B20 | C16: =NOL!C20 | D16: =NOL!D20 | E16: =NOL!E20 | F16: =NOL!F20
A17: Minimum tax floor (최저한세) | B17: =NOL!B21 | C17: =NOL!C21 | D17: =NOL!D21 | E17: =NOL!E21 | F17: =NOL!F21 | H17: A FLOOR on credit usage, not a cap on tax. Applies to the base AFTER the NOL deduction.
A18: less credits used | B18: =-NOL!B23 | C18: =-NOL!C23 | D18: =-NOL!D23 | E18: =-NOL!E23 | F18: =-NOL!F23 | H18: 4.61bn pool; offsets tax only down to the floor.
A19: Cash tax | B19: =MAX(B16-NOL!B23,0) | C19: =MAX(C16-NOL!C23,0) | D19: =MAX(D16-NOL!D23,0) | E19: =MAX(E16-NOL!E23,0) | F19: =MAX(F16-NOL!F23,0)
A20: NOPAT | B20: =B10-B19 | C20: =C10-C19 | D20: =D10-D19 | E20: =E10-E19 | F20: =F10-F19
A22: add D&A | B22: =Assumptions!$B$16 | C22: =Assumptions!$B$16 | D22: =Assumptions!$B$16 | E22: =Assumptions!$B$16 | F22: =Assumptions!$B$16
A23: less Capex | B23: =-Assumptions!$B$15 | C23: =-Assumptions!$B$15 | D23: =-Assumptions!$B$15 | E23: =-Assumptions!$B$15 | F23: =-Assumptions!$B$15
A24: NWC | B24: =B6*Assumptions!$B$12 | C24: =C6*Assumptions!$B$12 | D24: =D6*Assumptions!$B$12 | E24: =E6*Assumptions!$B$12 | F24: =F6*Assumptions!$B$12
A25: less change in NWC | B25: =-(B24-37.35) | C25: =-(C24-B24) | D25: =-(D24-C24) | E25: =-(E24-D24) | F25: =-(F24-E24) | H25: FY25 actual NWC = 37.35bn is the opening base. THE swing factor — see README.
A26: Free cash flow | B26: =B20+B22+B23+B25 | C26: =C20+C22+C23+C25 | D26: =D20+D22+D23+D25 | E26: =E20+E22+E23+E25 | F26: =F20+F22+F23+F25
A27: Discount factor | B27: =1/(1+Assumptions!$B$17)^1 | C27: =1/(1+Assumptions!$B$17)^2 | D27: =1/(1+Assumptions!$B$17)^3 | E27: =1/(1+Assumptions!$B$17)^4 | F27: =1/(1+Assumptions!$B$17)^5
A28: PV of FCF | B28: =B26*B27 | C28: =C26*C27 | D28: =D26*D27 | E28: =E26*E27 | F28: =F26*F27
A30: VALUATION BRIDGE
A31: Sum PV of explicit FCF | B31: =SUM(B28:F28)
A32: Terminal value (Gordon) | B32: =F26*(1+Assumptions!$B$18)/(Assumptions!$B$17-Assumptions!$B$18) | D32: Breaks down if terminal FCF is negative — check the FCF line before trusting this.
A33: PV of terminal value | B33: =B32*F27
A34: TV as % of EV | B34: =IFERROR(B33/(B31+B33),0) | D34: If this is >80%, the DCF is an exit-multiple guess wearing a cash-flow costume.
A35: Enterprise value | B35: =B31+B33
A36: add Investment property | B36: =Assumptions!$B$28 | D36: Non-operating, at book. Not a valuation.
A37: less Net debt | B37: =-Assumptions!$B$27
A38: Equity value | B38: =B35+B36+B37
A39: Shares (M) | B39: =Assumptions!$B$26
A40: Value per share (KRW) | B40: =IFERROR(B38*1000/B39,0) | D40: Excludes convertible-bond dilution (7.46bn CB outstanding).
A41: Last traded price (KRW) | B41: 9140 | D41: 45,700 on 2026-07-03 / 5 for the split. Stock SUSPENDED 07-07..07-24; not a live quote.
A42: Upside / (downside) | B42: =IFERROR(B40/B41-1,0)

Sheet Sensitivity
A1: SENSITIVITY — value per share (KRW)
A3: Excel recalculates these only via Data > What-If > Data Table, or just change the Assumptions inputs and watch Model!B40.
A5: The grid below is a MANUAL reference: set WACC / terminal growth on Assumptions and read the result. Automating it needs a Data Table, which openpyxl cannot emit.
A7: WACC \ terminal g | B7: 0 | C7: 0.01 | D7: 0.02 | E7: 0.03 | F7: 0.04
A8: 0.08 | B8: — | C8: — | D8: — | E8: — | F8: —
A9: 0.1 | B9: — | C9: — | D9: — | E9: — | F9: —
A10: 0.12 | B10: — | C10: — | D10: — | E10: — | F10: —
A11: 0.14 | B11: — | C11: — | D11: — | E11: — | F11: —
A12: 0.16 | B12: — | C12: — | D12: — | E12: — | F12: —
A14: Terminal value will likely be most of EV. Before reading any number above as a fair value, check Model!B34 (TV as % of EV) and confirm terminal FCF is positive — if WC is still building at the terminal year, Gordon growth on a negative FCF produces a meaningless negative TV.
